MANIFEST.in
setup.cfg
setup.py
versioneer.py
pynapi/__init__.py
pynapi/_version.py
pynapi/cmdline.py
pynapi/exc.py
pynapi.egg-info/PKG-INFO
pynapi.egg-info/SOURCES.txt
pynapi.egg-info/dependency_links.txt
pynapi.egg-info/entry_points.txt
pynapi.egg-info/pbr.json
pynapi.egg-info/top_level.txt
pynapi/services/__init__.py
pynapi/services/napiprojekt.py