Metadata-Version: 1.0
Name: pynapi
Version: 0.5.7
Summary: subtitles downloader
Home-page: https://github.com/jabbas/pynapi
Author: Grzegorz Dzięgielewski
Author-email: jabbas@jabbas.eu
License: GPLv3
Platform: UNKNOWN
